hrtps/starposition/__init__.py
hrtps/starposition/thriftio/STARService.py
hrtps/starposition/thriftio/__init__.py
hrtps/starposition/thriftio/constants.py
hrtps/starposition/thriftio/ttypes.py
thrift_ctx/__init__.py
thrift_ctx/ctx.py
thrift_ctx/logconf.py
thrift_ctx-0.1.5.dist-info/METADATA
thrift_ctx-0.1.5.dist-info/WHEEL
thrift_ctx-0.1.5.dist-info/top_level.txt
thrift_ctx-0.1.5.dist-info/RECORD
