Metadata-Version: 2.1
Name: thrift-ctx
Version: 0.1.5
Summary: thrift context
Home-page: UNKNOWN
Author: csc
Author-email: caishc@hrtps.com
License: UNKNOWN
Platform: UNKNOWN
Requires-Python: >=3.6
Requires-Dist: Werkzeug
Requires-Dist: thrift
